LICENSE
citation_langserver/__init__.py
citation_langserver/__main__.py
citation_langserver/bibliography.py
citation_langserver/cli.py
citation_langserver/completion.py
citation_langserver/document.py
citation_langserver/format.py
citation_langserver/server.py
citation_langserver-0.2.2.dist-info/entry_points.txt
citation_langserver-0.2.2.dist-info/LICENSE
citation_langserver-0.2.2.dist-info/WHEEL
citation_langserver-0.2.2.dist-info/METADATA
citation_langserver-0.2.2.dist-info/RECORD
